{"is_source_file": false, "format": "CSS", "description": "This file contains CSS variable definitions and styles for theming a web application's frontend, including theme toggling, layout, typography, and responsiveness. It includes styles for light and dark themes, as well as specific UI components like buttons and status messages.", "external_files": [], "external_methods": [], "published": [], "classes": [], "methods": [], "calls": [], "search-terms": ["CSS Variables", "theming", "Ocean Professional Theme", "dark mode styles", "responsive design", "UI component styles"], "state": 2, "file_id": 3, "knowledge_revision": 45, "git_revision": "66a184e367ab586d7bc851f28ee721e41f3de03d", "hash": "28ceae5d7456779b5fa0a965dbdc7dc9", "format-version": 4, "code-base-name": "tic_tac_toe_frontend", "filename": "tic_tac_toe_frontend/src/App.css", "revision_history": [{"45": "66a184e367ab586d7bc851f28ee721e41f3de03d"}]}